pingala_shunya/__init__.py
pingala_shunya/cli.py
pingala_shunya/transcriber.py
pingala_shunya-0.1.7.dist-info/licenses/LICENSE
pingala_shunya-0.1.7.dist-info/METADATA
pingala_shunya-0.1.7.dist-info/WHEEL
pingala_shunya-0.1.7.dist-info/entry_points.txt
pingala_shunya-0.1.7.dist-info/top_level.txt
pingala_shunya-0.1.7.dist-info/RECORD
