Metadata-Version: 2.4
Name: pingala-shunya
Version: 0.1.7
Summary: Speech transcription package by Shunya Labs with ct2 and transformers backends
Author-email: Shunya Labs <0@shunyalabs.ai>
Project-URL: Homepage, https://shunyalabs.ai
Project-URL: Documentation, https://shunyalabs.ai/pingala-shunya
Project-URL: Bug Reports, https://github.com/Shunyalabsai/pingala-shunya/issues
Project-URL: Source, https://github.com/Shunyalabsai/pingala-shunya
Keywords: speech-to-text,transcription,audio,ai,shunyalabs,ct2,transformers,enterprise
Classifier: Development Status :: 4 - Beta
Classifier: Intended Audience :: Developers
Classifier: License :: OSI Approved :: MIT License
Classifier: Operating System :: OS Independent
Classifier: Programming Language :: Python :: 3
Classifier: Programming Language :: Python :: 3.8
Classifier: Programming Language :: Python :: 3.9
Classifier: Programming Language :: Python :: 3.10
Classifier: Programming Language :: Python :: 3.11
Classifier: Programming Language :: Python :: 3.12
Classifier: Topic :: Multimedia :: Sound/Audio :: Speech
Classifier: Topic :: Scientific/Engineering :: Artificial Intelligence
Requires-Python: >=3.8
License-File: LICENSE
Requires-Dist: faster-whisper>=0.10.0
Requires-Dist: torch>=1.9.0
Requires-Dist: torchaudio>=0.9.0
Requires-Dist: transformers==4.52.4
Requires-Dist: ctranslate2==4.4.0
Requires-Dist: librosa>=0.10.0
Requires-Dist: datasets>=2.0.0
Requires-Dist: numpy>=1.21.0
Provides-Extra: dev
Requires-Dist: pytest>=6.0; extra == "dev"
Requires-Dist: pytest-cov>=2.0; extra == "dev"
Requires-Dist: black>=21.0; extra == "dev"
Requires-Dist: flake8>=3.8; extra == "dev"
Requires-Dist: mypy>=0.900; extra == "dev"
Provides-Extra: complete
Requires-Dist: pytest>=6.0; extra == "complete"
Requires-Dist: pytest-cov>=2.0; extra == "complete"
Requires-Dist: black>=21.0; extra == "complete"
Requires-Dist: flake8>=3.8; extra == "complete"
Requires-Dist: mypy>=0.900; extra == "complete"
Dynamic: license-file
